cacheall/__init__.py
cacheall/cache_dec.py
cacheall/cachetest.py
cacheall/dictionary.py
cacheall/Algorithms/__init__.py
cacheall/Algorithms/dllnode.py
cacheall/Algorithms/doublylinkedlist.py
cacheall/EvictionPolicies/FIFOevictionpolicy.py
cacheall/EvictionPolicies/LIFOevictionpolicy.py
cacheall/EvictionPolicies/LRUevictionpolicy.py
cacheall/EvictionPolicies/__init__.py
cacheall/EvictionPolicies/verbose.py
cacheall-0.1.7.dist-info/METADATA
cacheall-0.1.7.dist-info/WHEEL
cacheall-0.1.7.dist-info/top_level.txt
cacheall-0.1.7.dist-info/RECORD
